libsegmenter/AsymmetricWindowSelector.py
libsegmenter/Segmenter.py
libsegmenter/TransformSelector.py
libsegmenter/Window.py
libsegmenter/WindowSelector.py
libsegmenter/__init__.py
libsegmenter/backends/SegmenterNumpy.py
libsegmenter/backends/SegmenterTensorFlow.py
libsegmenter/backends/SegmenterTorch.py
libsegmenter/backends/__init__.py
libsegmenter/backends/common.py
libsegmenter/transforms/BPD.py
libsegmenter/transforms/MagnitudePhase.py
libsegmenter/transforms/Spectrogram.py
libsegmenter/transforms/__init__.py
libsegmenter/transforms/magnitude_phase/MagnitudePhaseNumpy.py
libsegmenter/transforms/magnitude_phase/MagnitudePhaseTensorFlow.py
libsegmenter/transforms/magnitude_phase/MagnitudePhaseTorch.py
libsegmenter/transforms/magnitude_phase/__init__.py
libsegmenter/transforms/spectrogram/SpectrogramNumpy.py
libsegmenter/transforms/spectrogram/SpectrogramTensorFlow.py
libsegmenter/transforms/spectrogram/SpectrogramTorch.py
libsegmenter/transforms/spectrogram/__init__.py
libsegmenter/util/__init__.py
libsegmenter/util/check_cola.py
libsegmenter/windows/__init__.py
libsegmenter/windows/bartlett.py
libsegmenter/windows/blackman.py
libsegmenter/windows/hamming.py
libsegmenter/windows/hann.py
libsegmenter/windows/kaiser.py
libsegmenter/windows/rectangular.py
libsegmenter-1.0.9.dist-info/METADATA
libsegmenter-1.0.9.dist-info/WHEEL
libsegmenter-1.0.9.dist-info/top_level.txt
libsegmenter-1.0.9.dist-info/RECORD
