Metadata-Version: 2.4
Name: libsegmenter
Version: 1.0.9
Summary: An opinionated segmentation library for (machine learning) audio
Requires-Python: >=3.10
Requires-Dist: numpy==1.26.4
Requires-Dist: scipy>=1.15.2
Provides-Extra: torch
Requires-Dist: torch>=2.6.0; extra == "torch"
Provides-Extra: octave
Requires-Dist: oct2py>=5.8.0; extra == "octave"
Provides-Extra: tensorflow
Requires-Dist: tensorflow-cpu>=2.14.0; extra == "tensorflow"
